Metadata-Version: 2.1
Name: icl-sharpy
Version: 2.3
Summary: SHARPy is a nonlinear aeroelastic analysis package developed
Home-page: https://github.com/ImperialCollegeLondon/sharpy
Author: 
Author-email: 
License: BSD 3-Clause License
Keywords: nonlinear aeroelastic structural aerodynamic analysis
Classifier: Operating System :: MacOS
Classifier: Operating System :: POSIX :: Linux
Classifier: Programming Language :: Python :: 3.10
Classifier: Programming Language :: Fortran
Classifier: Programming Language :: C++
Requires-Python: >=3.8
License-File: LICENSE
Requires-Dist: numpy<2.0
Requires-Dist: configobj
Requires-Dist: h5py
Requires-Dist: scipy<1.14.0
Requires-Dist: sympy
Requires-Dist: matplotlib
Requires-Dist: colorama
Requires-Dist: dill
Requires-Dist: jupyterlab
Requires-Dist: mayavi
Requires-Dist: pandas
Requires-Dist: control
Requires-Dist: openpyxl>=3.0.10
Requires-Dist: lxml>=4.4.1
Requires-Dist: PySocks
Requires-Dist: PyYAML
Provides-Extra: all
Requires-Dist: sphinx; extra == "all"
Requires-Dist: recommonmark>=0.6.0; extra == "all"
Requires-Dist: sphinx-rtd-theme>=0.4.3; extra == "all"
Requires-Dist: nbsphinx>=0.4.3; extra == "all"
Provides-Extra: docs
Requires-Dist: sphinx; extra == "docs"
Requires-Dist: recommonmark>=0.6.0; extra == "docs"
Requires-Dist: sphinx-rtd-theme>=0.4.3; extra == "docs"
Requires-Dist: nbsphinx>=0.4.3; extra == "docs"
